phonepe_transaction/__init__.py
phonepe_transaction/env_details.py
phonepe_transaction/generate_transactionID.py
phonepe_transaction/payment.py
phonepe_transaction-1.1.dist-info/licenses/LICENSE
phonepe_transaction-1.1.dist-info/METADATA
phonepe_transaction-1.1.dist-info/WHEEL
phonepe_transaction-1.1.dist-info/top_level.txt
phonepe_transaction-1.1.dist-info/RECORD
